odoo9_addon_mail_as_letter-9.0.1.0.0.99.dev10-py2.7-nspkg.pth
odoo9_addon_mail_as_letter-9.0.1.0.0.99.dev10.dist-info/DESCRIPTION.rst
odoo9_addon_mail_as_letter-9.0.1.0.0.99.dev10.dist-info/METADATA
odoo9_addon_mail_as_letter-9.0.1.0.0.99.dev10.dist-info/RECORD
odoo9_addon_mail_as_letter-9.0.1.0.0.99.dev10.dist-info/WHEEL
odoo9_addon_mail_as_letter-9.0.1.0.0.99.dev10.dist-info/metadata.json
odoo9_addon_mail_as_letter-9.0.1.0.0.99.dev10.dist-info/namespace_packages.txt
odoo9_addon_mail_as_letter-9.0.1.0.0.99.dev10.dist-info/top_level.txt
odoo_addons/mail_as_letter/README.rst
odoo_addons/mail_as_letter/__init__.py
odoo_addons/mail_as_letter/__openerp__.py
odoo_addons/mail_as_letter/i18n/ca.po
odoo_addons/mail_as_letter/i18n/de.po
odoo_addons/mail_as_letter/i18n/es.po
odoo_addons/mail_as_letter/i18n/es_CO.po
odoo_addons/mail_as_letter/i18n/fr.po
odoo_addons/mail_as_letter/i18n/hr.po
odoo_addons/mail_as_letter/i18n/mail_as_letter.pot
odoo_addons/mail_as_letter/i18n/pt_BR.po
odoo_addons/mail_as_letter/i18n/sl.po
odoo_addons/mail_as_letter/i18n/zh_CN.po
odoo_addons/mail_as_letter/report/mail_as_letter_qweb.xml
odoo_addons/mail_as_letter/static/description/icon.png
odoo_addons/mail_as_letter/tests/__init__.py
odoo_addons/mail_as_letter/tests/test_mail_as_letter.py
odoo_addons/mail_as_letter/wizards/__init__.py
odoo_addons/mail_as_letter/wizards/mail_compose_message.py
odoo_addons/mail_as_letter/wizards/mail_compose_message.xml
